hydra_server/__init__.py
hydra_server/commands.py
hydra_server/run.py
hydra_server/plugins/__init__.py
hydra_server/plugins/advanced_dataset_retrieval.py
hydra_server/plugins/ra_collections.py
hydra_server/plugins/sample.py
hydra_server/plugins/timeseries_functions.py
hydra_server/server/__init__.py
hydra_server/server/attributes.py
hydra_server/server/complexmodels.py
hydra_server/server/data.py
hydra_server/server/groups.py
hydra_server/server/network.py
hydra_server/server/notes.py
hydra_server/server/plugins.py
hydra_server/server/project.py
hydra_server/server/rules.py
hydra_server/server/scenario.py
hydra_server/server/service.py
hydra_server/server/sharing.py
hydra_server/server/static.py
hydra_server/server/template.py
hydra_server/server/units.py
hydra_server/server/users.py
hydra_server-0.1.3.dist-info/METADATA
hydra_server-0.1.3.dist-info/RECORD
hydra_server-0.1.3.dist-info/WHEEL
hydra_server-0.1.3.dist-info/dependency_links.txt
hydra_server-0.1.3.dist-info/entry_points.txt
hydra_server-0.1.3.dist-info/top_level.txt
